omnipose/__init__.py
omnipose/__main__.py
omnipose/core.py
omnipose/utils.py
omnipose/__pycache__/__init__.cpython-38.pyc
omnipose/__pycache__/core.cpython-38.pyc
omnipose/__pycache__/core.cpython-39.pyc
omnipose/__pycache__/utils.cpython-38.pyc
omnipose/__pycache__/utils.cpython-39.pyc
omnipose_acdc-0.3.5.dist-info/LICENSE
omnipose_acdc-0.3.5.dist-info/METADATA
omnipose_acdc-0.3.5.dist-info/WHEEL
omnipose_acdc-0.3.5.dist-info/top_level.txt
omnipose_acdc-0.3.5.dist-info/RECORD
