Metadata-Version: 2.1
Name: omnipose-acdc
Version: 0.3.5
Summary: cell segmentation algorithm improving on the Cellpose framework
Home-page: https://github.com/kevinjohncutler/omnipose
Author: Francesco Padovani
Author-email: padovaf@tcd.ie
Classifier: Programming Language :: Python :: 3
Classifier: Operating System :: OS Independent
License-File: LICENSE
Requires-Dist: numpy >=1.22.4
Requires-Dist: scipy
Requires-Dist: numba
Requires-Dist: edt
Requires-Dist: scikit-image
Requires-Dist: ncolor
Requires-Dist: scikit-learn
Requires-Dist: mahotas >=1.4.13
Requires-Dist: cellpose-omni-acdc >=0.6.8
Requires-Dist: mgen
